RedPy/__init__.py
RedPy/redpy.py
RedPy-0.0.3.dist-info/METADATA
RedPy-0.0.3.dist-info/RECORD
RedPy-0.0.3.dist-info/WHEEL
RedPy-0.0.3.dist-info/top_level.txt
